openbb_pydantic_ai/__init__.py
openbb_pydantic_ai/_adapter.py
openbb_pydantic_ai/_config.py
openbb_pydantic_ai/_dependencies.py
openbb_pydantic_ai/_event_builder.py
openbb_pydantic_ai/_event_stream.py
openbb_pydantic_ai/_event_stream_components.py
openbb_pydantic_ai/_event_stream_helpers.py
openbb_pydantic_ai/_exceptions.py
openbb_pydantic_ai/_message_transformer.py
openbb_pydantic_ai/_serializers.py
openbb_pydantic_ai/_toolsets.py
openbb_pydantic_ai/_types.py
openbb_pydantic_ai/_utils.py
openbb_pydantic_ai/_widget_registry.py
openbb_pydantic_ai-0.1.5.dist-info/WHEEL
openbb_pydantic_ai-0.1.5.dist-info/METADATA
openbb_pydantic_ai-0.1.5.dist-info/RECORD
