Metadata-Version: 2.3
Name: openbb-pydantic-ai
Version: 0.1.5
Summary: Pydantic AI adapter for OpenBB SDK. Enables connettion any pydantic-ai agent to the OpenBB Workspace.
Author: Magnus Samuelsen
License: MIT
Requires-Dist: openbb-ai>=1.7.6
Requires-Dist: pydantic-ai-slim>=1.14.0
Requires-Python: >=3.10
